pxdbench/__init__.py
pxdbench-0.1.0.dist-info/METADATA
pxdbench-0.1.0.dist-info/WHEEL
pxdbench-0.1.0.dist-info/top_level.txt
pxdbench-0.1.0.dist-info/RECORD
