Metadata-Version: 2.4
Name: pxdbench
Version: 0.1.0
Summary: POC package (beacon-only)
Author: Your Name
Requires-Python: >=3.6
